Metadata-Version: 2.1
Name: htmltabletomd
Version: 1.0.0
Summary: Convert html table to markdown table
Home-page: https://github.com/vsavo/htmltabletomd
Author: Vijeyraj Savoundiraradjou
Author-email: vijeysavy@gmail.com
License: MIT
Keywords: markdown tables
Platform: UNKNOWN
Classifier: License :: OSI Approved :: MIT License
Classifier: Programming Language :: Python :: 3
Classifier: Programming Language :: Python :: 3 :: Only
Classifier: Programming Language :: Python :: 3.6
Classifier: Programming Language :: Python :: 3.7
Classifier: Programming Language :: Python :: 3.8
Requires-Python: >=3.6.1
